plexiglass/__init__.py
plexiglass/model.py
plexiglass/version
plexiglass/DNN/__init__.py
plexiglass/DNN/attacks/__init__.py
plexiglass/DNN/attacks/deepfool.py
plexiglass/DNN/attacks/fgsm.py
plexiglass/DNN/attacks/jsma.py
plexiglass/DNN/attacks/pgd.py
plexiglass/DNN/attacks/testing.py
plexiglass/DNN/defense/__init__.py
plexiglass/DNN/defense/mesonet.py
plexiglass/LLM/__init__.py
plexiglass/LLM/evaluate.py
plexiglass/LLM/attacks/__init__.py
plexiglass/LLM/attacks/gcg.py
plexiglass/LLM/attacks/injection.py
plexiglass/LLM/defense/__init__.py
plexiglass-0.0.1.dist-info/LICENSE
plexiglass-0.0.1.dist-info/METADATA
plexiglass-0.0.1.dist-info/WHEEL
plexiglass-0.0.1.dist-info/top_level.txt
plexiglass-0.0.1.dist-info/RECORD
