Metadata-Version: 2.1
Name: plexiglass
Version: 0.0.1
Summary: A Python Machine Learning Security Toolbox for Adversarial Attacks.
Author-email: Chi Nok Enoch Kan <your-email@example.com>
License: Apache License
Project-URL: Homepage, https://github.com/kortex-labs/plexiglass
Project-URL: Issues, https://github.com/kortex-labs/plexiglass/issues
Keywords: adversarial,DNN,LLM
Classifier: Programming Language :: Python
Classifier: Programming Language :: Python :: 3
Requires-Python: >=3.6
License-File: LICENSE
Requires-Dist: torch >=1.7.0
Requires-Dist: litellm
Requires-Dist: detoxify
